glowbuzzer/__init__.py
glowbuzzer/gbp/__init__.py
glowbuzzer/gbp/client.py
glowbuzzer/gbp/connection.py
glowbuzzer/gbp/gbc.py
glowbuzzer/gbp/gbc_extra.py
glowbuzzer/gbp/logger.py
glowbuzzer/gbp/machine_state.py
glowbuzzer/gbp/effects/debug.py
glowbuzzer/gbp/effects/heartbeat.py
glowbuzzer/gbp/effects/op.py
glowbuzzer/gbp/effects/solo_activity.py
glowbuzzer/gbp/effects/stream.py
glowbuzzer/gbp/effects/types.py
glowbuzzer/gbp/effects/input/digital.py
glowbuzzer/gbp/ros/__init__.py
glowbuzzer/gbp/ros/decorator.py
glowbuzzer/gbp/ros/logger.py
glowbuzzer/gbp/ros/spinner.py
glowbuzzer_gbp-1.0.4.dist-info/LICENSE
glowbuzzer_gbp-1.0.4.dist-info/METADATA
glowbuzzer_gbp-1.0.4.dist-info/WHEEL
glowbuzzer_gbp-1.0.4.dist-info/top_level.txt
glowbuzzer_gbp-1.0.4.dist-info/RECORD
