Metadata-Version: 2.1
Name: glowbuzzer-gbp
Version: 1.0.4
Summary: glowbuzzer Python API (GBP)
Author-email: glowbuzzer <hello@glowbuzzer.com>
License: MIT
Classifier: Programming Language :: Python :: 3
Classifier: License :: OSI Approved :: MIT License
Classifier: Operating System :: OS Independent
License-File: LICENSE
Requires-Dist: websockets~=13.1
Requires-Dist: pydantic~=2.9.2
Provides-Extra: test
Requires-Dist: pytest~=8.3.3; extra == "test"
Requires-Dist: pytest-asyncio~=0.16.0; extra == "test"
